{
	"animations": [
		{
			"loop": false,
			"offsets": [
				-20,
				10
			],
			"anim": "idle",
			"fps": 24,
			"name": "idle",
			"indices": []
		},
		{
			"loop": false,
			"offsets": [
				-31,
				34
			],
			"anim": "singUP",
			"fps": 24,
			"name": "up",
			"indices": []
		},
		{
			"loop": false,
			"offsets": [
				-60,
				3
			],
			"anim": "singRIGHT",
			"fps": 24,
			"name": "right",
			"indices": []
		},
		{
			"loop": false,
			"offsets": [
				21,
				-2
			],
			"anim": "singLEFT",
			"fps": 24,
			"name": "left",
			"indices": []
		},
		{
			"loop": false,
			"offsets": [
				-61,
				1
			],
			"anim": "singDOWN",
			"fps": 24,
			"name": "down",
			"indices": []
		}
	],
	"no_antialiasing": false,
	"image": "characters/kenny",
	"position": [
		0,
		270
	],
	"healthicon": "kenny",
	"flip_x": false,
	"healthbar_colors": [
		153,
		82,
		0
	],
	"camera_position": [
		40,
		20
	],
	"sing_duration": 4,
	"scale": 1
}